setup.py
cuscatlan/__init__.py
cuscatlan/elemental.py
cuscatlan.egg-info/PKG-INFO
cuscatlan.egg-info/SOURCES.txt
cuscatlan.egg-info/dependency_links.txt
cuscatlan.egg-info/not-zip-safe
cuscatlan.egg-info/requires.txt
cuscatlan.egg-info/top_level.txt