Metadata-Version: 1.0
Name: cuscatlan
Version: 0.0.2
Summary: Edwin Juarez's personal library
Home-page: https://github.com/edjuaro/cuscatlan
Author: Edwin F. Juarez
Author-email: ejuarez@ucsd.edu
License: MIT
Platform: UNKNOWN
